{
  "version": "7",
  "dialect": "postgresql",
  "entries": [
    {
      "idx": 0,
      "version": "7",
      "when": 1773373908426,
      "tag": "0000_demonic_malcolm_colcord",
      "breakpoints": true
    },
    {
      "idx": 1,
      "version": "7",
      "when": 1773374482470,
      "tag": "0001_fast_polaris",
      "breakpoints": true
    },
    {
      "idx": 2,
      "version": "7",
      "when": 1773518607626,
      "tag": "0002_overjoyed_spiral",
      "breakpoints": true
    },
    {
      "idx": 3,
      "version": "7",
      "when": 1774188015441,
      "tag": "0003_high_nemesis",
      "breakpoints": true
    }
  ]
}